nucleusapp_telegram/__init__.py
nucleusapp_telegram/app.py
nucleusapp_telegram/base.py
nucleusapp_telegram/settings_example.py
nucleusapp_telegram/static.py
nucleusapp_telegram/utils.py
nucleusapp_telegram-0.2.2.dist-info/DESCRIPTION.rst
nucleusapp_telegram-0.2.2.dist-info/METADATA
nucleusapp_telegram-0.2.2.dist-info/RECORD
nucleusapp_telegram-0.2.2.dist-info/WHEEL
nucleusapp_telegram-0.2.2.dist-info/metadata.json
nucleusapp_telegram-0.2.2.dist-info/top_level.txt
