Metadata-Version: 2.0
Name: nucleusapp-telegram
Version: 0.2.2
Summary: Telegram module for NucleusApp based on pyTelegramBotAPI
Home-page: https://bitbucket.org/illemius/nucleusapp_telegram
Author: Illemius/Alex Root Junior
Author-email: jroot.junio@gmail.com
License: MIT
Keywords: Illemius,NucleusUtils,NucleusApp,TelegramUtilities
Platform: UNKNOWN
Classifier: Development Status :: 5 - Production/Stable
Classifier: Intended Audience :: Developers
Classifier: Intended Audience :: Education
Classifier: Intended Audience :: End Users/Desktop
Classifier: Intended Audience :: System Administrators
Classifier: License :: OSI Approved :: MIT License
Classifier: Programming Language :: Python
Classifier: Programming Language :: Python :: 3.6
Classifier: Topic :: Software Development :: Libraries :: Python Modules
Classifier: Topic :: Utilities
Requires-Dist: NucleusApp
Requires-Dist: NucleusUtils
Requires-Dist: TeleSocketClient
Requires-Dist: pyTelegramBotAPI
